{
	"recordsFiltered" : 26,
	"data" : [{
			"buttonMap" : {},
			"company" : null,
			"companyCode" : "",
			"companyId" : 8,
			"companyName" : "百度人才",
			"createDate" : null,
			"createUserId" : 0,
			"createUserName" : "",
			"failtureTime" : 0,
			"isLocked" : 0,
			"isValid" : 1,
			"lastChangePasswordDate" : null,
			"lastModifyDate" : null,
			"lastModifyUserId" : 22,
			"lastModifyUserName" : "公司系统管理员",
			"locked" : "未锁定",
			"loginTime" : 0,
			"mailAddress" : "zhenyu.liu@ezhiyang.com",
			"memo" : "",
			"mobile" : "",
			"modifyDate" : "2015-12-30 17:03",
			"password" : "",
			"sex" : 0,
			"telephone" : "",
			"userCode" : "1111",
			"userDistinguish" : "",
			"userId" : 73,
			"userName" : "刘振宇叔叔",
			"userType" : 2,
			"utype" : "系统管理员",
			"valid" : "有效"
		}, {
			"buttonMap" : {},
			"company" : null,
			"companyCode" : "",
			"companyId" : 8,
			"companyName" : "百度人才",
			"createDate" : null,
			"createUserId" : 0,
			"createUserName" : "",
			"failtureTime" : 0,
			"isLocked" : 0,
			"isValid" : 1,
			"lastChangePasswordDate" : null,
			"lastModifyDate" : null,
			"lastModifyUserId" : 22,
			"lastModifyUserName" : "公司系统管理员",
			"locked" : "未锁定",
			"loginTime" : 0,
			"mailAddress" : "pengyurou94@163.com",
			"memo" : "",
			"mobile" : "",
			"modifyDate" : "2015-12-18 14:38",
			"password" : "",
			"sex" : 0,
			"telephone" : "",
			"userCode" : "ggfdhj",
			"userDistinguish" : "",
			"userId" : 72,
			"userName" : "dfgd",
			"userType" : 3,
			"utype" : "普通用户",
			"valid" : "有效"
		}, {
			"buttonMap" : {},
			"company" : null,
			"companyCode" : "",
			"companyId" : 8,
			"companyName" : "百度人才",
			"createDate" : null,
			"createUserId" : 0,
			"createUserName" : "",
			"failtureTime" : 0,
			"isLocked" : 0,
			"isValid" : 1,
			"lastChangePasswordDate" : null,
			"lastModifyDate" : null,
			"lastModifyUserId" : 22,
			"lastModifyUserName" : "公司系统管理员",
			"locked" : "未锁定",
			"loginTime" : 0,
			"mailAddress" : "gdsgdf@qq.com",
			"memo" : "",
			"mobile" : "",
			"modifyDate" : "2015-12-18 14:32",
			"password" : "",
			"sex" : 0,
			"telephone" : "",
			"userCode" : "ffdgfd",
			"userDistinguish" : "",
			"userId" : 71,
			"userName" : "gdssf",
			"userType" : 3,
			"utype" : "普通用户",
			"valid" : "有效"
		}, {
			"buttonMap" : {},
			"company" : null,
			"companyCode" : "",
			"companyId" : 8,
			"companyName" : "百度人才",
			"createDate" : null,
			"createUserId" : 0,
			"createUserName" : "",
			"failtureTime" : 0,
			"isLocked" : 0,
			"isValid" : 1,
			"lastChangePasswordDate" : null,
			"lastModifyDate" : null,
			"lastModifyUserId" : 22,
			"lastModifyUserName" : "公司系统管理员",
			"locked" : "未锁定",
			"loginTime" : 0,
			"mailAddress" : "pengyurou94@163.com",
			"memo" : "",
			"mobile" : "",
			"modifyDate" : "2015-12-18 13:08",
			"password" : "",
			"sex" : 0,
			"telephone" : "",
			"userCode" : "ffdsf",
			"userDistinguish" : "",
			"userId" : 70,
			"userName" : "fdsff",
			"userType" : 3,
			"utype" : "普通用户",
			"valid" : "有效"
		}, {
			"buttonMap" : {},
			"company" : null,
			"companyCode" : "",
			"companyId" : 8,
			"companyName" : "百度人才",
			"createDate" : null,
			"createUserId" : 0,
			"createUserName" : "",
			"failtureTime" : 0,
			"isLocked" : 0,
			"isValid" : 1,
			"lastChangePasswordDate" : null,
			"lastModifyDate" : null,
			"lastModifyUserId" : 22,
			"lastModifyUserName" : "公司系统管理员",
			"locked" : "未锁定",
			"loginTime" : 0,
			"mailAddress" : "fdfgfdsg@qq.com",
			"memo" : "",
			"mobile" : "",
			"modifyDate" : "2015-12-18 13:05",
			"password" : "",
			"sex" : 0,
			"telephone" : "",
			"userCode" : "gsdfg",
			"userDistinguish" : "",
			"userId" : 69,
			"userName" : "放散阀",
			"userType" : 3,
			"utype" : "普通用户",
			"valid" : "有效"
		}, {
			"buttonMap" : {},
			"company" : null,
			"companyCode" : "",
			"companyId" : 8,
			"companyName" : "百度人才",
			"createDate" : null,
			"createUserId" : 0,
			"createUserName" : "",
			"failtureTime" : 0,
			"isLocked" : 0,
			"isValid" : 1,
			"lastChangePasswordDate" : null,
			"lastModifyDate" : null,
			"lastModifyUserId" : 22,
			"lastModifyUserName" : "公司系统管理员",
			"locked" : "未锁定",
			"loginTime" : 0,
			"mailAddress" : "fsdfd@qq.com",
			"memo" : "",
			"mobile" : "",
			"modifyDate" : "2015-12-18 13:02",
			"password" : "",
			"sex" : 0,
			"telephone" : "",
			"userCode" : "vdfg",
			"userDistinguish" : "",
			"userId" : 68,
			"userName" : "发的方法",
			"userType" : 3,
			"utype" : "普通用户",
			"valid" : "有效"
		}, {
			"buttonMap" : {},
			"company" : null,
			"companyCode" : "",
			"companyId" : 8,
			"companyName" : "百度人才",
			"createDate" : null,
			"createUserId" : 0,
			"createUserName" : "",
			"failtureTime" : 0,
			"isLocked" : 0,
			"isValid" : 1,
			"lastChangePasswordDate" : null,
			"lastModifyDate" : null,
			"lastModifyUserId" : 22,
			"lastModifyUserName" : "公司系统管理员",
			"locked" : "未锁定",
			"loginTime" : 0,
			"mailAddress" : "dffsfdss@qq.com",
			"memo" : "",
			"mobile" : "",
			"modifyDate" : "2015-12-18 12:51",
			"password" : "",
			"sex" : 0,
			"telephone" : "",
			"userCode" : "dsfds",
			"userDistinguish" : "",
			"userId" : 67,
			"userName" : "fd辅导费",
			"userType" : 3,
			"utype" : "普通用户",
			"valid" : "有效"
		}, {
			"buttonMap" : {},
			"company" : null,
			"companyCode" : "",
			"companyId" : 8,
			"companyName" : "百度人才",
			"createDate" : null,
			"createUserId" : 0,
			"createUserName" : "",
			"failtureTime" : 0,
			"isLocked" : 0,
			"isValid" : 1,
			"lastChangePasswordDate" : null,
			"lastModifyDate" : null,
			"lastModifyUserId" : 22,
			"lastModifyUserName" : "公司系统管理员",
			"locked" : "未锁定",
			"loginTime" : 0,
			"mailAddress" : "22@qq.com",
			"memo" : "",
			"mobile" : "",
			"modifyDate" : "2015-12-18 12:39",
			"password" : "",
			"sex" : 0,
			"telephone" : "",
			"userCode" : "QQQ",
			"userDistinguish" : "",
			"userId" : 66,
			"userName" : "都是",
			"userType" : 3,
			"utype" : "普通用户",
			"valid" : "有效"
		}, {
			"buttonMap" : {},
			"company" : null,
			"companyCode" : "",
			"companyId" : 8,
			"companyName" : "百度人才",
			"createDate" : null,
			"createUserId" : 0,
			"createUserName" : "",
			"failtureTime" : 0,
			"isLocked" : 0,
			"isValid" : 1,
			"lastChangePasswordDate" : null,
			"lastModifyDate" : null,
			"lastModifyUserId" : 22,
			"lastModifyUserName" : "公司系统管理员",
			"locked" : "未锁定",
			"loginTime" : 0,
			"mailAddress" : "fsfds@qq.com",
			"memo" : "",
			"mobile" : "",
			"modifyDate" : "2015-12-18 12:38",
			"password" : "",
			"sex" : 0,
			"telephone" : "",
			"userCode" : "fddsf",
			"userDistinguish" : "",
			"userId" : 65,
			"userName" : "方式发送到",
			"userType" : 3,
			"utype" : "普通用户",
			"valid" : "有效"
		}, {
			"buttonMap" : {},
			"company" : null,
			"companyCode" : "",
			"companyId" : 8,
			"companyName" : "百度人才",
			"createDate" : null,
			"createUserId" : 0,
			"createUserName" : "",
			"failtureTime" : 0,
			"isLocked" : 0,
			"isValid" : 1,
			"lastChangePasswordDate" : null,
			"lastModifyDate" : null,
			"lastModifyUserId" : 22,
			"lastModifyUserName" : "公司系统管理员",
			"locked" : "未锁定",
			"loginTime" : 0,
			"mailAddress" : "fdskfj@163.com",
			"memo" : "",
			"mobile" : "",
			"modifyDate" : "2015-12-18 12:23",
			"password" : "",
			"sex" : 0,
			"telephone" : "",
			"userCode" : "gfdf",
			"userDistinguish" : "",
			"userId" : 64,
			"userName" : "房顶上放放大",
			"userType" : 3,
			"utype" : "普通用户",
			"valid" : "有效"
		}, {
			"buttonMap" : {},
			"company" : null,
			"companyCode" : "",
			"companyId" : 8,
			"companyName" : "百度人才",
			"createDate" : null,
			"createUserId" : 0,
			"createUserName" : "",
			"failtureTime" : 0,
			"isLocked" : 0,
			"isValid" : 1,
			"lastChangePasswordDate" : null,
			"lastModifyDate" : null,
			"lastModifyUserId" : 22,
			"lastModifyUserName" : "公司系统管理员",
			"locked" : "未锁定",
			"loginTime" : 0,
			"mailAddress" : "fdsfs@qq.com",
			"memo" : "",
			"mobile" : "",
			"modifyDate" : "2015-12-18 12:20",
			"password" : "",
			"sex" : 0,
			"telephone" : "",
			"userCode" : "hkh",
			"userDistinguish" : "",
			"userId" : 63,
			"userName" : "辅导费发的",
			"userType" : 3,
			"utype" : "普通用户",
			"valid" : "有效"
		}, {
			"buttonMap" : {},
			"company" : null,
			"companyCode" : "",
			"companyId" : 8,
			"companyName" : "百度人才",
			"createDate" : null,
			"createUserId" : 0,
			"createUserName" : "",
			"failtureTime" : 0,
			"isLocked" : 0,
			"isValid" : 1,
			"lastChangePasswordDate" : null,
			"lastModifyDate" : null,
			"lastModifyUserId" : 22,
			"lastModifyUserName" : "公司系统管理员",
			"locked" : "未锁定",
			"loginTime" : 0,
			"mailAddress" : "faf@qq.com",
			"memo" : "",
			"mobile" : "",
			"modifyDate" : "2015-12-17 20:23",
			"password" : "",
			"sex" : 0,
			"telephone" : "",
			"userCode" : "fd",
			"userDistinguish" : "",
			"userId" : 62,
			"userName" : "fdasfa",
			"userType" : 3,
			"utype" : "普通用户",
			"valid" : "有效"
		}, {
			"buttonMap" : {},
			"company" : null,
			"companyCode" : "",
			"companyId" : 8,
			"companyName" : "百度人才",
			"createDate" : null,
			"createUserId" : 0,
			"createUserName" : "",
			"failtureTime" : 0,
			"isLocked" : 0,
			"isValid" : 1,
			"lastChangePasswordDate" : null,
			"lastModifyDate" : null,
			"lastModifyUserId" : 7,
			"lastModifyUserName" : "管理员",
			"locked" : "未锁定",
			"loginTime" : 0,
			"mailAddress" : "yq.wang@ezhiyang.com",
			"memo" : "",
			"mobile" : "",
			"modifyDate" : "2015-12-16 18:49",
			"password" : "",
			"sex" : 0,
			"telephone" : "",
			"userCode" : "hhh",
			"userDistinguish" : "",
			"userId" : 61,
			"userName" : "呜呜",
			"userType" : 3,
			"utype" : "普通用户",
			"valid" : "有效"
		}, {
			"buttonMap" : {},
			"company" : null,
			"companyCode" : "",
			"companyId" : 8,
			"companyName" : "百度人才",
			"createDate" : null,
			"createUserId" : 0,
			"createUserName" : "",
			"failtureTime" : 0,
			"isLocked" : 0,
			"isValid" : 1,
			"lastChangePasswordDate" : null,
			"lastModifyDate" : null,
			"lastModifyUserId" : 7,
			"lastModifyUserName" : "管理员",
			"locked" : "未锁定",
			"loginTime" : 0,
			"mailAddress" : "747177410@qq.com",
			"memo" : "",
			"mobile" : "",
			"modifyDate" : "2015-12-15 17:51",
			"password" : "",
			"sex" : 0,
			"telephone" : "",
			"userCode" : "vb",
			"userDistinguish" : "",
			"userId" : 53,
			"userName" : "ZZ",
			"userType" : 3,
			"utype" : "普通用户",
			"valid" : "有效"
		}, {
			"buttonMap" : {},
			"company" : null,
			"companyCode" : "",
			"companyId" : 8,
			"companyName" : "百度人才",
			"createDate" : null,
			"createUserId" : 0,
			"createUserName" : "",
			"failtureTime" : 0,
			"isLocked" : 0,
			"isValid" : 1,
			"lastChangePasswordDate" : null,
			"lastModifyDate" : null,
			"lastModifyUserId" : 7,
			"lastModifyUserName" : "管理员",
			"locked" : "未锁定",
			"loginTime" : 0,
			"mailAddress" : "747177410@qq.com",
			"memo" : "",
			"mobile" : "",
			"modifyDate" : "2015-12-15 17:34",
			"password" : "",
			"sex" : 0,
			"telephone" : "",
			"userCode" : "eee",
			"userDistinguish" : "",
			"userId" : 48,
			"userName" : "dd",
			"userType" : 3,
			"utype" : "普通用户",
			"valid" : "有效"
		}, {
			"buttonMap" : {},
			"company" : null,
			"companyCode" : "",
			"companyId" : 8,
			"companyName" : "百度人才",
			"createDate" : null,
			"createUserId" : 0,
			"createUserName" : "",
			"failtureTime" : 0,
			"isLocked" : 0,
			"isValid" : 1,
			"lastChangePasswordDate" : null,
			"lastModifyDate" : null,
			"lastModifyUserId" : 7,
			"lastModifyUserName" : "管理员",
			"locked" : "未锁定",
			"loginTime" : 0,
			"mailAddress" : "747177410@qq.com",
			"memo" : "",
			"mobile" : "",
			"modifyDate" : "2015-12-15 17:28",
			"password" : "",
			"sex" : 0,
			"telephone" : "",
			"userCode" : "zs",
			"userDistinguish" : "",
			"userId" : 46,
			"userName" : "小五",
			"userType" : 3,
			"utype" : "普通用户",
			"valid" : "有效"
		}, {
			"buttonMap" : {},
			"company" : null,
			"companyCode" : "",
			"companyId" : 8,
			"companyName" : "百度人才",
			"createDate" : null,
			"createUserId" : 0,
			"createUserName" : "",
			"failtureTime" : 0,
			"isLocked" : 0,
			"isValid" : 1,
			"lastChangePasswordDate" : null,
			"lastModifyDate" : null,
			"lastModifyUserId" : 22,
			"lastModifyUserName" : "公司系统管理员",
			"locked" : "未锁定",
			"loginTime" : 0,
			"mailAddress" : "747177410@qq.com",
			"memo" : "",
			"mobile" : "",
			"modifyDate" : "2015-12-15 15:56",
			"password" : "",
			"sex" : 0,
			"telephone" : "",
			"userCode" : "R80000",
			"userDistinguish" : "",
			"userId" : 36,
			"userName" : "小四",
			"userType" : 2,
			"utype" : "系统管理员",
			"valid" : "有效"
		}, {
			"buttonMap" : {},
			"company" : null,
			"companyCode" : "",
			"companyId" : 8,
			"companyName" : "百度人才",
			"createDate" : null,
			"createUserId" : 0,
			"createUserName" : "",
			"failtureTime" : 0,
			"isLocked" : 0,
			"isValid" : 0,
			"lastChangePasswordDate" : null,
			"lastModifyDate" : null,
			"lastModifyUserId" : 22,
			"lastModifyUserName" : "公司系统管理员",
			"locked" : "未锁定",
			"loginTime" : 0,
			"mailAddress" : "835613696@qq.com",
			"memo" : "",
			"mobile" : "",
			"modifyDate" : "2015-12-08 10:05",
			"password" : "",
			"sex" : 0,
			"telephone" : "",
			"userCode" : "abc",
			"userDistinguish" : "",
			"userId" : 34,
			"userName" : "张三",
			"userType" : 3,
			"utype" : "普通用户",
			"valid" : "无效"
		}, {
			"buttonMap" : {},
			"company" : null,
			"companyCode" : "",
			"companyId" : 8,
			"companyName" : "百度人才",
			"createDate" : null,
			"createUserId" : 0,
			"createUserName" : "",
			"failtureTime" : 0,
			"isLocked" : 0,
			"isValid" : 0,
			"lastChangePasswordDate" : null,
			"lastModifyDate" : null,
			"lastModifyUserId" : 22,
			"lastModifyUserName" : "公司系统管理员",
			"locked" : "未锁定",
			"loginTime" : 0,
			"mailAddress" : "1243@qq.com",
			"memo" : "",
			"mobile" : "",
			"modifyDate" : "2015-12-08 09:43",
			"password" : "",
			"sex" : 0,
			"telephone" : "",
			"userCode" : "123",
			"userDistinguish" : "",
			"userId" : 32,
			"userName" : "dfgfda",
			"userType" : 3,
			"utype" : "普通用户",
			"valid" : "无效"
		}, {
			"buttonMap" : {},
			"company" : null,
			"companyCode" : "",
			"companyId" : 8,
			"companyName" : "百度人才",
			"createDate" : null,
			"createUserId" : 0,
			"createUserName" : "",
			"failtureTime" : 0,
			"isLocked" : 0,
			"isValid" : 1,
			"lastChangePasswordDate" : null,
			"lastModifyDate" : null,
			"lastModifyUserId" : 22,
			"lastModifyUserName" : "公司系统管理员",
			"locked" : "未锁定",
			"loginTime" : 0,
			"mailAddress" : "1242@qq.com",
			"memo" : "",
			"mobile" : "",
			"modifyDate" : "2015-12-08 09:41",
			"password" : "",
			"sex" : 0,
			"telephone" : "",
			"userCode" : "324",
			"userDistinguish" : "",
			"userId" : 31,
			"userName" : "讽德诵功",
			"userType" : 2,
			"utype" : "系统管理员",
			"valid" : "有效"
		}, {
			"buttonMap" : {},
			"company" : null,
			"companyCode" : "",
			"companyId" : 8,
			"companyName" : "百度人才",
			"createDate" : null,
			"createUserId" : 0,
			"createUserName" : "",
			"failtureTime" : 0,
			"isLocked" : 0,
			"isValid" : 0,
			"lastChangePasswordDate" : null,
			"lastModifyDate" : null,
			"lastModifyUserId" : 22,
			"lastModifyUserName" : "公司系统管理员",
			"locked" : "未锁定",
			"loginTime" : 0,
			"mailAddress" : "dsadsa@ss.coin",
			"memo" : "",
			"mobile" : "",
			"modifyDate" : "2015-12-04 18:41",
			"password" : "",
			"sex" : 0,
			"telephone" : "",
			"userCode" : "123",
			"userDistinguish" : "",
			"userId" : 30,
			"userName" : "sadas",
			"userType" : 2,
			"utype" : "系统管理员",
			"valid" : "无效"
		}, {
			"buttonMap" : {},
			"company" : null,
			"companyCode" : "",
			"companyId" : 8,
			"companyName" : "百度人才",
			"createDate" : null,
			"createUserId" : 0,
			"createUserName" : "",
			"failtureTime" : 0,
			"isLocked" : 0,
			"isValid" : 0,
			"lastChangePasswordDate" : null,
			"lastModifyDate" : null,
			"lastModifyUserId" : 22,
			"lastModifyUserName" : "公司系统管理员",
			"locked" : "未锁定",
			"loginTime" : 0,
			"mailAddress" : "abc@del.com",
			"memo" : "",
			"mobile" : "",
			"modifyDate" : "2015-12-04 18:40",
			"password" : "",
			"sex" : 0,
			"telephone" : "",
			"userCode" : "001",
			"userDistinguish" : "",
			"userId" : 26,
			"userName" : "abc",
			"userType" : 3,
			"utype" : "普通用户",
			"valid" : "无效"
		}, {
			"buttonMap" : {},
			"company" : null,
			"companyCode" : "",
			"companyId" : 8,
			"companyName" : "百度人才",
			"createDate" : null,
			"createUserId" : 0,
			"createUserName" : "",
			"failtureTime" : 0,
			"isLocked" : 0,
			"isValid" : 0,
			"lastChangePasswordDate" : null,
			"lastModifyDate" : null,
			"lastModifyUserId" : 22,
			"lastModifyUserName" : "公司系统管理员",
			"locked" : "未锁定",
			"loginTime" : 0,
			"mailAddress" : "weiping@baijob.com",
			"memo" : "",
			"mobile" : "",
			"modifyDate" : "2012-06-19 19:27",
			"password" : "",
			"sex" : 0,
			"telephone" : "",
			"userCode" : "weiping",
			"userDistinguish" : "",
			"userId" : 25,
			"userName" : "魏平",
			"userType" : 3,
			"utype" : "普通用户",
			"valid" : "无效"
		}, {
			"buttonMap" : {},
			"company" : null,
			"companyCode" : "",
			"companyId" : 8,
			"companyName" : "百度人才",
			"createDate" : null,
			"createUserId" : 0,
			"createUserName" : "",
			"failtureTime" : 0,
			"isLocked" : 0,
			"isValid" : 1,
			"lastChangePasswordDate" : null,
			"lastModifyDate" : null,
			"lastModifyUserId" : 22,
			"lastModifyUserName" : "公司系统管理员",
			"locked" : "未锁定",
			"loginTime" : 0,
			"mailAddress" : "lina.wang@ct-hr.com",
			"memo" : "",
			"mobile" : "",
			"modifyDate" : "2012-05-26 09:19",
			"password" : "",
			"sex" : 0,
			"telephone" : "",
			"userCode" : "wanglina",
			"userDistinguish" : "",
			"userId" : 24,
			"userName" : "王丽娜",
			"userType" : 2,
			"utype" : "系统管理员",
			"valid" : "有效"
		}, {
			"buttonMap" : {},
			"company" : null,
			"companyCode" : "",
			"companyId" : 8,
			"companyName" : "百度人才",
			"createDate" : null,
			"createUserId" : 0,
			"createUserName" : "",
			"failtureTime" : 0,
			"isLocked" : 0,
			"isValid" : 1,
			"lastChangePasswordDate" : null,
			"lastModifyDate" : null,
			"lastModifyUserId" : 22,
			"lastModifyUserName" : "公司系统管理员",
			"locked" : "未锁定",
			"loginTime" : 0,
			"mailAddress" : "jllu@asti.com.cn",
			"memo" : "",
			"mobile" : "",
			"modifyDate" : "2012-05-04 23:12",
			"password" : "",
			"sex" : 0,
			"telephone" : "",
			"userCode" : "test",
			"userDistinguish" : "",
			"userId" : 23,
			"userName" : "测试",
			"userType" : 3,
			"utype" : "普通用户",
			"valid" : "有效"
		}, {
			"buttonMap" : {},
			"company" : null,
			"companyCode" : "",
			"companyId" : 8,
			"companyName" : "百度人才",
			"createDate" : null,
			"createUserId" : 0,
			"createUserName" : "",
			"failtureTime" : 0,
			"isLocked" : 0,
			"isValid" : 1,
			"lastChangePasswordDate" : null,
			"lastModifyDate" : null,
			"lastModifyUserId" : 7,
			"lastModifyUserName" : "管理员",
			"locked" : "未锁定",
			"loginTime" : 0,
			"mailAddress" : "jllu@asti.com.cn",
			"memo" : "",
			"mobile" : "",
			"modifyDate" : "2012-05-04 23:05",
			"password" : "",
			"sex" : 0,
			"telephone" : "",
			"userCode" : "lujianliang",
			"userDistinguish" : "",
			"userId" : 22,
			"userName" : "公司系统管理员",
			"userType" : 2,
			"utype" : "系统管理员",
			"valid" : "有效"
		}
	],
	"recordsTotal" : 26,
	"user" : {
		"buttonMap" : {},
		"company" : null,
		"companyCode" : "",
		"companyId" : 8,
		"companyName" : "",
		"createDate" : null,
		"createUserId" : 0,
		"createUserName" : "",
		"failtureTime" : 0,
		"isLocked" : 0,
		"isValid" : 0,
		"lastChangePasswordDate" : null,
		"lastModifyDate" : null,
		"lastModifyUserId" : 0,
		"lastModifyUserName" : "",
		"locked" : "",
		"loginTime" : 0,
		"mailAddress" : "",
		"memo" : "",
		"mobile" : "",
		"modifyDate" : "",
		"password" : "",
		"sex" : 0,
		"telephone" : "",
		"userCode" : "",
		"userDistinguish" : "",
		"userId" : 0,
		"userName" : "",
		"userType" : 0,
		"utype" : "",
		"valid" : ""
	}
}
