<?xml version="1.0" encoding="UTF-8" ?>
<!DOCTYPE mapper PUBLIC "-//mybatis.org//DTD Mapper 3.0//EN" "http://mybatis.org/dtd/mybatis-3-mapper.dtd" >
<mapper namespace="com.jabava.dao.common.EhrCommonDataMapper" >
  <resultMap id="BaseResultMap" type="com.jabava.pojo.common.EhrCommonData" >
    <!--
      WARNING - @mbggenerated
      This element is automatically generated by MyBatis Generator, do not modify.
      This element was generated on Tue Apr 12 12:05:38 CST 2016.
    -->
    <id column="common_data_id" property="commonDataId" jdbcType="BIGINT" />
    <result column="common_data_type" property="commonDataType" jdbcType="INTEGER" />
    <result column="common_data_code" property="commonDataCode" jdbcType="VARCHAR" />
    <result column="common_data_name" property="commonDataName" jdbcType="VARCHAR" />
    <result column="memo" property="memo" jdbcType="VARCHAR" />
    <result column="is_valid" property="isValid" jdbcType="TINYINT" />
    <result column="create_user_id" property="createUserId" jdbcType="BIGINT" />
    <result column="create_user_name" property="createUserName" jdbcType="VARCHAR" />
    <result column="create_date" property="createDate" jdbcType="TIMESTAMP" />
    <result column="last_modify_user_id" property="lastModifyUserId" jdbcType="BIGINT" />
    <result column="last_modify_user_name" property="lastModifyUserName" jdbcType="VARCHAR" />
    <result column="last_modify_date" property="lastModifyDate" jdbcType="TIMESTAMP" />
  </resultMap>
  <sql id="Base_Column_List" >
    <!--
      WARNING - @mbggenerated
      This element is automatically generated by MyBatis Generator, do not modify.
      This element was generated on Tue Apr 12 12:05:38 CST 2016.
    -->
    common_data_id, common_data_type, common_data_code, common_data_name, memo, is_valid, 
    create_user_id, create_user_name, create_date, last_modify_user_id, last_modify_user_name, 
    last_modify_date
  </sql>
  <select id="selectByPrimaryKey" resultMap="BaseResultMap" parameterType="java.lang.Long" >
    <!--
      WARNING - @mbggenerated
      This element is automatically generated by MyBatis Generator, do not modify.
      This element was generated on Tue Apr 12 12:05:38 CST 2016.
    -->
    select 
    <include refid="Base_Column_List" />
    from ehr_common_data
    where common_data_id = #{commonDataId,jdbcType=BIGINT}
  </select>
  <delete id="deleteByPrimaryKey" parameterType="java.lang.Long" >
    <!--
      WARNING - @mbggenerated
      This element is automatically generated by MyBatis Generator, do not modify.
      This element was generated on Tue Apr 12 12:05:38 CST 2016.
    -->
    delete from ehr_common_data
    where common_data_id = #{commonDataId,jdbcType=BIGINT}
  </delete>
  <insert id="insert" parameterType="com.jabava.pojo.common.EhrCommonData" >
    <!--
      WARNING - @mbggenerated
      This element is automatically generated by MyBatis Generator, do not modify.
      This element was generated on Tue Apr 12 12:05:38 CST 2016.
    -->
    insert into ehr_common_data (common_data_id, common_data_type, common_data_code, 
      common_data_name, memo, is_valid, 
      create_user_id, create_user_name, create_date, 
      last_modify_user_id, last_modify_user_name, last_modify_date
      )
    values (#{commonDataId,jdbcType=BIGINT}, #{commonDataType,jdbcType=INTEGER}, #{commonDataCode,jdbcType=VARCHAR}, 
      #{commonDataName,jdbcType=VARCHAR}, #{memo,jdbcType=VARCHAR}, #{isValid,jdbcType=TINYINT}, 
      #{createUserId,jdbcType=BIGINT}, #{createUserName,jdbcType=VARCHAR}, #{createDate,jdbcType=TIMESTAMP}, 
      #{lastModifyUserId,jdbcType=BIGINT}, #{lastModifyUserName,jdbcType=VARCHAR}, #{lastModifyDate,jdbcType=TIMESTAMP}
      )
  </insert>
  <insert id="insertSelective" parameterType="com.jabava.pojo.common.EhrCommonData" >
    <!--
      WARNING - @mbggenerated
      This element is automatically generated by MyBatis Generator, do not modify.
      This element was generated on Tue Apr 12 12:05:38 CST 2016.
    -->
    insert into ehr_common_data
    <trim prefix="(" suffix=")" suffixOverrides="," >
      <if test="commonDataId != null" >
        common_data_id,
      </if>
      <if test="commonDataType != null" >
        common_data_type,
      </if>
      <if test="commonDataCode != null" >
        common_data_code,
      </if>
      <if test="commonDataName != null" >
        common_data_name,
      </if>
      <if test="memo != null" >
        memo,
      </if>
      <if test="isValid != null" >
        is_valid,
      </if>
      <if test="createUserId != null" >
        create_user_id,
      </if>
      <if test="createUserName != null" >
        create_user_name,
      </if>
      <if test="createDate != null" >
        create_date,
      </if>
      <if test="lastModifyUserId != null" >
        last_modify_user_id,
      </if>
      <if test="lastModifyUserName != null" >
        last_modify_user_name,
      </if>
      <if test="lastModifyDate != null" >
        last_modify_date,
      </if>
    </trim>
    <trim prefix="values (" suffix=")" suffixOverrides="," >
      <if test="commonDataId != null" >
        #{commonDataId,jdbcType=BIGINT},
      </if>
      <if test="commonDataType != null" >
        #{commonDataType,jdbcType=INTEGER},
      </if>
      <if test="commonDataCode != null" >
        #{commonDataCode,jdbcType=VARCHAR},
      </if>
      <if test="commonDataName != null" >
        #{commonDataName,jdbcType=VARCHAR},
      </if>
      <if test="memo != null" >
        #{memo,jdbcType=VARCHAR},
      </if>
      <if test="isValid != null" >
        #{isValid,jdbcType=TINYINT},
      </if>
      <if test="createUserId != null" >
        #{createUserId,jdbcType=BIGINT},
      </if>
      <if test="createUserName != null" >
        #{createUserName,jdbcType=VARCHAR},
      </if>
      <if test="createDate != null" >
        #{createDate,jdbcType=TIMESTAMP},
      </if>
      <if test="lastModifyUserId != null" >
        #{lastModifyUserId,jdbcType=BIGINT},
      </if>
      <if test="lastModifyUserName != null" >
        #{lastModifyUserName,jdbcType=VARCHAR},
      </if>
      <if test="lastModifyDate != null" >
        #{lastModifyDate,jdbcType=TIMESTAMP},
      </if>
    </trim>
  </insert>
  <update id="updateByPrimaryKeySelective" parameterType="com.jabava.pojo.common.EhrCommonData" >
    <!--
      WARNING - @mbggenerated
      This element is automatically generated by MyBatis Generator, do not modify.
      This element was generated on Tue Apr 12 12:05:38 CST 2016.
    -->
    update ehr_common_data
    <set >
      <if test="commonDataType != null" >
        common_data_type = #{commonDataType,jdbcType=INTEGER},
      </if>
      <if test="commonDataCode != null" >
        common_data_code = #{commonDataCode,jdbcType=VARCHAR},
      </if>
      <if test="commonDataName != null" >
        common_data_name = #{commonDataName,jdbcType=VARCHAR},
      </if>
      <if test="memo != null" >
        memo = #{memo,jdbcType=VARCHAR},
      </if>
      <if test="isValid != null" >
        is_valid = #{isValid,jdbcType=TINYINT},
      </if>
      <if test="createUserId != null" >
        create_user_id = #{createUserId,jdbcType=BIGINT},
      </if>
      <if test="createUserName != null" >
        create_user_name = #{createUserName,jdbcType=VARCHAR},
      </if>
      <if test="createDate != null" >
        create_date = #{createDate,jdbcType=TIMESTAMP},
      </if>
      <if test="lastModifyUserId != null" >
        last_modify_user_id = #{lastModifyUserId,jdbcType=BIGINT},
      </if>
      <if test="lastModifyUserName != null" >
        last_modify_user_name = #{lastModifyUserName,jdbcType=VARCHAR},
      </if>
      <if test="lastModifyDate != null" >
        last_modify_date = #{lastModifyDate,jdbcType=TIMESTAMP},
      </if>
    </set>
    where common_data_id = #{commonDataId,jdbcType=BIGINT}
  </update>
  <update id="updateByPrimaryKey" parameterType="com.jabava.pojo.common.EhrCommonData" >
    <!--
      WARNING - @mbggenerated
      This element is automatically generated by MyBatis Generator, do not modify.
      This element was generated on Tue Apr 12 12:05:38 CST 2016.
    -->
    update ehr_common_data
    set common_data_type = #{commonDataType,jdbcType=INTEGER},
      common_data_code = #{commonDataCode,jdbcType=VARCHAR},
      common_data_name = #{commonDataName,jdbcType=VARCHAR},
      memo = #{memo,jdbcType=VARCHAR},
      is_valid = #{isValid,jdbcType=TINYINT},
      create_user_id = #{createUserId,jdbcType=BIGINT},
      create_user_name = #{createUserName,jdbcType=VARCHAR},
      create_date = #{createDate,jdbcType=TIMESTAMP},
      last_modify_user_id = #{lastModifyUserId,jdbcType=BIGINT},
      last_modify_user_name = #{lastModifyUserName,jdbcType=VARCHAR},
      last_modify_date = #{lastModifyDate,jdbcType=TIMESTAMP}
    where common_data_id = #{commonDataId,jdbcType=BIGINT}
  </update>
  
  <select id="listByCommonDataType" resultMap="BaseResultMap">
  	select * from ehr_common_data where common_data_type=#{commonDataType,jdbcType=INTEGER}
  </select>
  <select id="selectByTypeAndCode" resultMap="BaseResultMap">
  	select * from ehr_common_data 
  	where common_data_type=#{commonDataType,jdbcType=INTEGER} and common_data_code = #{commonDataCode,jdbcType=VARCHAR}
  </select>
</mapper>